{"graphs":[{"name":"graph0","node_types":["E","J"],"link_types":["in","con"],"nodes":[{"key":2,"label":"E","color":"#637939","width":18,"height":18,"visible_label":[{"text":"E","color":"black"}]}],"links":[]}],
"generative_grammar_rules":[{"name":"left inherence","node_types":["E","S"],"link_types":["sv","in"],"nac_count":4,"nodes":[{"key":0,"label":"E","color":"black","width":64,"height":15,"definition":"type:E","visible_label":[{"text":"[1]:E","color":"black"}]},{"key":1,"label":"E","color":"green","width":24,"height":15,"definition":"new::type:E","visible_label":[{"text":"E","color":"green"}]}],"links":[{"key":"1-0_new::type:in","source":1,"target":0,"label":"in","color":"green","definition":"new::type:in","marker_id":"in","visible_label":[{"text":"in","color":"green"}]}]},{"name":"right inherence","node_types":["E","S"],"link_types":["sv","in"],"nac_count":3,"nodes":[{"key":0,"label":"E","color":"black","width":64,"height":15,"definition":"type:E","visible_label":[{"text":"[1]:E","color":"black"}]},{"key":1,"label":"E","color":"green","width":24,"height":15,"definition":"new::type:E","visible_label":[{"text":"E","color":"green"}]}],"links":[{"key":"0-1_new::type:in","source":0,"target":1,"label":"in","color":"green","definition":"new::type:in","marker_id":"in","visible_label":[{"text":"in","color":"green"}]}]}],
"NACs":[{"name":null,"node_types":["d"],"link_types":["f"],"nodes":[{"key":0,"label":"d","color":"#e7969c","width":18,"height":18,"visible_label":[{"text":"d","color":"black"}]},{"key":1,"label":"d","color":"#e7969c","width":18,"height":18,"visible_label":[{"text":"d","color":"black"}]}],"links":[{"key":"0-1_f","source":0,"target":1,"label":"f","color":"#a55194","marker_id":"f","visible_label":[{"text":"f","color":"black"}]}]},{"name":"right inherence NAC1","rule_name":"right inherence","rule_type":"Generative Rule","node_types":["E",""],"link_types":["in"],"nodes":[{"key":0,"label":"E","color":"black","width":44,"height":15,"definition":"type:E","visible_label":[{"text":"1:E","color":"black"}]},{"key":1,"label":"","color":"black","width":14,"height":15,"definition":"type:","visible_label":[{"text":"","color":"black"}]},{"key":2,"label":"","color":"black","width":14,"height":15,"definition":"type:","visible_label":[{"text":"","color":"black"}]},{"key":3,"label":"","color":"black","width":14,"height":15,"definition":"type:","visible_label":[{"text":"","color":"black"}]}],"links":[{"key":"3-2_type:in","source":3,"target":2,"label":"in","color":"black","marker_id":"in","definition":"type:in","visible_label":[{"text":"in","color":"black"}]},{"key":"2-1_type:in","source":2,"target":1,"label":"in","color":"black","marker_id":"in","definition":"type:in","visible_label":[{"text":"in","color":"black"}]},{"key":"1-0_type:in","source":1,"target":0,"label":"in","color":"black","marker_id":"in","definition":"type:in","visible_label":[{"text":"in","color":"black"}]}]},{"name":"conjunct NAC1","rule_name":"conjunct","rule_type":"Generative Rule","node_types":["E",""],"link_types":["in"],"nodes":[{"key":0,"label":"E","color":"black","width":44,"height":15,"definition":"type:E","visible_label":[{"text":"1:E","color":"black"}]},{"key":1,"label":"","color":"black","width":14,"height":15,"definition":"type:","visible_label":[{"text":"","color":"black"}]},{"key":2,"label":"","color":"black","width":14,"height":15,"definition":"type:","visible_label":[{"text":"","color":"black"}]}],"links":[{"key":"0-1_type:in","source":0,"target":1,"label":"in","color":"black","marker_id":"in","definition":"type:in","visible_label":[{"text":"in","color":"black"}]},{"key":"1-2_type:in","source":1,"target":2,"label":"in","color":"black","marker_id":"in","definition":"type:in","visible_label":[{"text":"in","color":"black"}]}]},{"name":"disjunct NAC1","rule_name":"disjunct","rule_type":"Generative Rule","node_types":["E",""],"link_types":["in"],"nodes":[{"key":0,"label":"E","color":"black","width":44,"height":15,"definition":"type:E","visible_label":[{"text":"1:E","color":"black"}]},{"key":1,"label":"","color":"black","width":14,"height":15,"definition":"type:","visible_label":[{"text":"","color":"black"}]},{"key":2,"label":"","color":"black","width":14,"height":15,"definition":"type:","visible_label":[{"text":"","color":"black"}]}],"links":[{"key":"0-1_type:in","source":0,"target":1,"label":"in","color":"black","marker_id":"in","definition":"type:in","visible_label":[{"text":"in","color":"black"}]},{"key":"1-2_type:in","source":1,"target":2,"label":"in","color":"black","marker_id":"in","definition":"type:in","visible_label":[{"text":"in","color":"black"}]}]},{"name":"right inherence NAC2","rule_name":"right inherence","rule_type":"Generative Rule","node_types":["E","J",""],"link_types":["in"],"nodes":[{"key":1,"label":"E","color":"black","width":44,"height":15,"definition":"type:E","visible_label":[{"text":"1:E","color":"black"}]},{"key":2,"label":"J","color":"black","width":24,"height":15,"definition":"type:J","visible_label":[{"text":"J","color":"black"}]},{"key":3,"label":"","color":"black","width":14,"height":15,"definition":"type:","visible_label":[{"text":"","color":"black"}]}],"links":[{"key":"2-3_type:in","source":1,"target":2,"label":"in","color":"black","marker_id":"in","definition":"type:in","visible_label":[{"text":"in","color":"black"}]},{"key":"3-1_type:in","source":2,"target":0,"label":"in","color":"black","marker_id":"in","definition":"type:in","visible_label":[{"text":"in","color":"black"}]}]},{"name":"left inherence NAC1","rule_name":"left inherence","rule_type":"Generative Rule","node_types":["E",""],"link_types":["in"],"nodes":[{"key":0,"label":"E","color":"black","width":44,"height":15,"definition":"type:E","visible_label":[{"text":"1:E","color":"black"}]},{"key":1,"label":"","color":"black","width":14,"height":15,"definition":"type:","visible_label":[{"text":"","color":"black"}]},{"key":2,"label":"","color":"black","width":14,"height":15,"definition":"type:","visible_label":[{"text":"","color":"black"}]},{"key":3,"label":"","color":"black","width":14,"height":15,"definition":"type:","visible_label":[{"text":"","color":"black"}]}],"links":[{"key":"0-1_type:in","source":0,"target":1,"label":"in","color":"black","marker_id":"in","definition":"type:in","visible_label":[{"text":"in","color":"black"}]},{"key":"1-3_type:in","source":1,"target":3,"label":"in","color":"black","marker_id":"in","definition":"type:in","visible_label":[{"text":"in","color":"black"}]},{"key":"3-2_type:in","source":3,"target":2,"label":"in","color":"black","marker_id":"in","definition":"type:in","visible_label":[{"text":"in","color":"black"}]}]},{"name":"left inherence NAC2","rule_name":"left inherence","rule_type":"Generative Rule","node_types":["E",""],"link_types":["in"],"nodes":[{"key":0,"label":"E","color":"black","width":44,"height":15,"definition":"type:E","visible_label":[{"text":"1:E","color":"black"}]},{"key":1,"label":"","color":"black","width":14,"height":15,"definition":"type:","visible_label":[{"text":"","color":"black"}]},{"key":2,"label":"","color":"black","width":14,"height":15,"definition":"type:","visible_label":[{"text":"","color":"black"}]},{"key":3,"label":"","color":"black","width":14,"height":15,"definition":"type:","visible_label":[{"text":"","color":"black"}]},{"key":4,"label":"","color":"black","width":14,"height":15,"definition":"type:","visible_label":[{"text":"","color":"black"}]},{"key":5,"label":"","color":"black","width":14,"height":15,"definition":"type:","visible_label":[{"text":"","color":"black"}]}],"links":[{"key":"0-2_type:in","source":0,"target":2,"label":"in","color":"black","marker_id":"in","definition":"type:in","visible_label":[{"text":"in","color":"black"}]},{"key":"2-3_type:in","source":2,"target":3,"label":"in","color":"black","marker_id":"in","definition":"type:in","visible_label":[{"text":"in","color":"black"}]},{"key":"5-3_type:in","source":5,"target":3,"label":"in","color":"black","marker_id":"in","definition":"type:in","visible_label":[{"text":"in","color":"black"}]},{"key":"4-5_type:in","source":4,"target":5,"label":"in","color":"black","marker_id":"in","definition":"type:in","visible_label":[{"text":"in","color":"black"}]},{"key":"1-4_type:in","source":1,"target":4,"label":"in","color":"black","marker_id":"in","definition":"type:in","visible_label":[{"text":"in","color":"black"}]}]},{"name":"left inherence NAC3","rule_name":"left inherence","rule_type":"Generative Rule","node_types":["E","J"],"link_types":["in"],"nodes":[{"key":0,"label":"E","color":"black","width":44,"height":15,"definition":"type:E","visible_label":[{"text":"1:E","color":"black"}]},{"key":1,"label":"J","color":"black","width":24,"height":15,"definition":"type:J","visible_label":[{"text":"J","color":"black"}]}],"links":[{"key":"0-1_type:in","source":0,"target":1,"label":"in","color":"black","marker_id":"in","definition":"type:in","visible_label":[{"text":"in","color":"black"}]}]},{"name":"left inherence NAC4","rule_name":"left inherence","rule_type":"Generative Rule","node_types":["E","D"],"link_types":["in"],"nodes":[{"key":0,"label":"E","color":"black","width":44,"height":15,"definition":"type:E","visible_label":[{"text":"1:E","color":"black"}]},{"key":1,"label":"D","color":"black","width":24,"height":15,"definition":"type:D","visible_label":[{"text":"D","color":"black"}]}],"links":[{"key":"0-1_type:in","source":0,"target":1,"label":"in","color":"black","marker_id":"in","definition":"type:in","visible_label":[{"text":"in","color":"black"}]}]},{"name":"inherence_conjunct NAC1","rule_name":"inherence_conjunct","rule_type":"Generative Rule","node_types":["E","J"],"link_types":["con","in"],"nodes":[{"key":0,"label":"E","color":"black","width":44,"height":15,"definition":"type:E","visible_label":[{"text":"2:E","color":"black"}]},{"key":1,"label":"E","color":"black","width":44,"height":15,"definition":"type:E","visible_label":[{"text":"1:E","color":"black"}]},{"key":2,"label":"J","color":"black","width":24,"height":15,"definition":"type:J","visible_label":[{"text":"J","color":"black"}]}],"links":[{"key":"1-0_type:con","source":1,"target":0,"label":"con","color":"black","marker_id":"con","definition":"type:con","visible_label":[{"text":"con","color":"black"}]},{"key":"0-1_type:con","source":0,"target":1,"label":"con","color":"black","marker_id":"con","definition":"type:con","visible_label":[{"text":"con","color":"black"}]},{"key":"2-0_type:in","source":2,"target":0,"label":"in","color":"black","marker_id":"in","definition":"type:in","visible_label":[{"text":"in","color":"black"}]},{"key":"2-1_type:in","source":2,"target":1,"label":"in","color":"black","marker_id":"in","definition":"type:in","visible_label":[{"text":"in","color":"black"}]}]},{"name":"inherence_conjunct NAC2","rule_name":"inherence_conjunct","rule_type":"Generative Rule","node_types":["E",""],"link_types":["in",""],"nodes":[{"key":0,"label":"E","color":"black","width":44,"height":15,"definition":"type:E","visible_label":[{"text":"1:E","color":"black"}]},{"key":1,"label":"","color":"black","width":14,"height":15,"definition":"type:","visible_label":[{"text":"","color":"black"}]},{"key":2,"label":"","color":"black","width":14,"height":15,"definition":"type:","visible_label":[{"text":"","color":"black"}]}],"links":[{"key":"0-1_type:in","source":0,"target":1,"label":"in","color":"black","marker_id":"in","definition":"type:in","visible_label":[{"text":"in","color":"black"}]},{"key":"1-2_type:in","source":1,"target":2,"label":"in","color":"black","marker_id":"in","definition":"type:in","visible_label":[{"text":"in","color":"black"}]}]},{"name":"inherence_conjunct NAC3","rule_name":"inherence_conjunct","rule_type":"Generative Rule","node_types":["E",""],"link_types":["in"],"nodes":[{"key":0,"label":"E","color":"black","width":44,"height":15,"definition":"type:E","visible_label":[{"text":"2:E","color":"black"}]},{"key":1,"label":"","color":"black","width":14,"height":15,"definition":"type:","visible_label":[{"text":"","color":"black"}]},{"key":2,"label":"","color":"black","width":14,"height":15,"definition":"type:","visible_label":[{"text":"","color":"black"}]}],"links":[{"key":"0-1_type:in","source":0,"target":1,"label":"in","color":"black","marker_id":"in","definition":"type:in","visible_label":[{"text":"in","color":"black"}]},{"key":"1-2_type:in","source":1,"target":2,"label":"in","color":"black","marker_id":"in","definition":"type:in","visible_label":[{"text":"in","color":"black"}]}]},{"name":"right inherence NAC3","rule_name":"right inherence","rule_type":"Generative Rule","node_types":["J","","E","D"],"link_types":["in"],"nodes":[{"key":2,"label":"E","color":"black","width":44,"height":15,"definition":"type:E","visible_label":[{"text":"1:E","color":"black"}]},{"key":3,"label":"D","color":"black","width":24,"height":15,"definition":"type:D","visible_label":[{"text":"D","color":"black"}]},{"key":4,"label":"","color":"black","width":14,"height":15,"definition":"type:","visible_label":[{"text":"","color":"black"}]}],"links":[{"key":"3-4_type:in","source":1,"target":2,"label":"in","color":"black","marker_id":"in","definition":"type:in","visible_label":[{"text":"in","color":"black"}]},{"key":"4-2_type:in","source":2,"target":0,"label":"in","color":"black","marker_id":"in","definition":"type:in","visible_label":[{"text":"in","color":"black"}]}]},{"name":"inherence_conjunct NAC4","rule_name":"inherence_conjunct","rule_type":"Generative Rule","node_types":["E","D"],"link_types":["dis","in"],"nodes":[{"key":0,"label":"E","color":"black","width":44,"height":15,"definition":"type:E","visible_label":[{"text":"2:E","color":"black"}]},{"key":1,"label":"E","color":"black","width":44,"height":15,"definition":"type:E","visible_label":[{"text":"1:E","color":"black"}]},{"key":2,"label":"D","color":"black","width":24,"height":15,"definition":"type:D","visible_label":[{"text":"D","color":"black"}]}],"links":[{"key":"1-0_type:dis","source":1,"target":0,"label":"dis","color":"black","marker_id":"dis","definition":"type:dis","visible_label":[{"text":"dis","color":"black"}]},{"key":"0-1_type:dis","source":0,"target":1,"label":"dis","color":"black","marker_id":"dis","definition":"type:dis","visible_label":[{"text":"dis","color":"black"}]},{"key":"2-1_type:in","source":2,"target":1,"label":"in","color":"black","marker_id":"in","definition":"type:in","visible_label":[{"text":"in","color":"black"}]},{"key":"2-0_type:in","source":2,"target":0,"label":"in","color":"black","marker_id":"in","definition":"type:in","visible_label":[{"text":"in","color":"black"}]}]},{"name":"inherence_disjunct NAC1","rule_name":"inherence_disjunct","rule_type":"Generative Rule","node_types":["E","D"],"link_types":["dis","in"],"nodes":[{"key":0,"label":"E","color":"black","width":44,"height":15,"definition":"type:E","visible_label":[{"text":"2:E","color":"black"}]},{"key":1,"label":"E","color":"black","width":44,"height":15,"definition":"type:E","visible_label":[{"text":"1:E","color":"black"}]},{"key":2,"label":"D","color":"black","width":24,"height":15,"definition":"type:D","visible_label":[{"text":"D","color":"black"}]}],"links":[{"key":"1-0_type:dis","source":1,"target":0,"label":"dis","color":"black","marker_id":"dis","definition":"type:dis","visible_label":[{"text":"dis","color":"black"}]},{"key":"0-1_type:dis","source":0,"target":1,"label":"dis","color":"black","marker_id":"dis","definition":"type:dis","visible_label":[{"text":"dis","color":"black"}]},{"key":"2-0_type:in","source":2,"target":0,"label":"in","color":"black","marker_id":"in","definition":"type:in","visible_label":[{"text":"in","color":"black"}]},{"key":"2-1_type:in","source":2,"target":1,"label":"in","color":"black","marker_id":"in","definition":"type:in","visible_label":[{"text":"in","color":"black"}]}]},{"name":"inherence_disjunct NAC2","rule_name":"inherence_disjunct","rule_type":"Generative Rule","node_types":["E",""],"link_types":["in"],"nodes":[{"key":0,"label":"E","color":"black","width":44,"height":15,"definition":"type:E","visible_label":[{"text":"1:E","color":"black"}]},{"key":1,"label":"","color":"black","width":14,"height":15,"definition":"type:","visible_label":[{"text":"","color":"black"}]},{"key":2,"label":"","color":"black","width":14,"height":15,"definition":"type:","visible_label":[{"text":"","color":"black"}]}],"links":[{"key":"0-1_type:in","source":0,"target":1,"label":"in","color":"black","marker_id":"in","definition":"type:in","visible_label":[{"text":"in","color":"black"}]},{"key":"1-2_type:in","source":1,"target":2,"label":"in","color":"black","marker_id":"in","definition":"type:in","visible_label":[{"text":"in","color":"black"}]}]},{"name":"inherence_disjunct NAC3","rule_name":"inherence_disjunct","rule_type":"Generative Rule","node_types":["E",""],"link_types":["in"],"nodes":[{"key":0,"label":"E","color":"black","width":44,"height":15,"definition":"type:E","visible_label":[{"text":"2:E","color":"black"}]},{"key":1,"label":"","color":"black","width":14,"height":15,"definition":"type:","visible_label":[{"text":"","color":"black"}]},{"key":2,"label":"","color":"black","width":14,"height":15,"definition":"type:","visible_label":[{"text":"","color":"black"}]}],"links":[{"key":"0-1_type:in","source":0,"target":1,"label":"in","color":"black","marker_id":"in","definition":"type:in","visible_label":[{"text":"in","color":"black"}]},{"key":"1-2_type:in","source":1,"target":2,"label":"in","color":"black","marker_id":"in","definition":"type:in","visible_label":[{"text":"in","color":"black"}]}]},{"name":"inherence_disjunct NAC4","rule_name":"inherence_disjunct","rule_type":"Generative Rule","node_types":["E","J"],"link_types":["con","in"],"nodes":[{"key":0,"label":"E","color":"black","width":44,"height":15,"definition":"type:E","visible_label":[{"text":"2:E","color":"black"}]},{"key":1,"label":"E","color":"black","width":44,"height":15,"definition":"type:E","visible_label":[{"text":"1:E","color":"black"}]},{"key":2,"label":"J","color":"black","width":24,"height":15,"definition":"type:J","visible_label":[{"text":"J","color":"black"}]}],"links":[{"key":"1-0_type:con","source":1,"target":0,"label":"con","color":"black","marker_id":"con","definition":"type:con","visible_label":[{"text":"con","color":"black"}]},{"key":"0-1_type:con","source":0,"target":1,"label":"con","color":"black","marker_id":"con","definition":"type:con","visible_label":[{"text":"con","color":"black"}]},{"key":"2-0_type:in","source":2,"target":0,"label":"in","color":"black","marker_id":"in","definition":"type:in","visible_label":[{"text":"in","color":"black"}]},{"key":"2-1_type:in","source":2,"target":1,"label":"in","color":"black","marker_id":"in","definition":"type:in","visible_label":[{"text":"in","color":"black"}]}]}],
"interpretation_rules":[{"name":"universal","node_types":["E","U",""],"link_types":["in"],"nac_count":0,"nodes":[{"key":0,"label":"E","color":"black","width":54,"height":30,"definition":"del:type:E;new:type:U","visible_label":[{"text":"[1,2]:-E","color":"blue"},{"text":"+U","color":"green"}]},{"key":1,"label":"","color":"black","width":14,"height":15,"definition":"type:","visible_label":[{"text":"","color":"black"}]},{"key":2,"label":"","color":"black","width":14,"height":15,"definition":"type:","visible_label":[{"text":"","color":"black"}]},{"key":3,"label":"","color":"red","width":14,"height":15,"definition":"not::type:","visible_label":[{"text":"","color":"red"}]}],"links":[{"key":"3-0_not::type:in","source":3,"target":0,"label":"in","color":"red","definition":"not::type:in","marker_id":"in","visible_label":[{"text":"in","color":"red"}]},{"key":"0-1_type:in","source":0,"target":1,"label":"in","color":"black","definition":"type:in","marker_id":"in","visible_label":[{"text":"in","color":"black"}]},{"key":"0-2_type:in","source":0,"target":2,"label":"in","color":"black","definition":"type:in","marker_id":"in","visible_label":[{"text":"in","color":"black"}]}]},{"name":"ultimate substance","node_types":["E","US",""],"link_types":["in"],"nac_count":0,"nodes":[{"key":0,"label":"E","color":"black","width":44,"height":30,"definition":"del:type:E;new:type:US","visible_label":[{"text":"-E","color":"blue"},{"text":"+US","color":"green"}]},{"key":1,"label":"","color":"red","width":14,"height":15,"definition":"not::type:","visible_label":[{"text":"","color":"red"}]}],"links":[{"key":"0-1_not::type:in","source":0,"target":1,"label":"in","color":"red","definition":"not::type:in","marker_id":"in","visible_label":[{"text":"in","color":"red"}]}]},{"name":"visesa","node_types":["US","E","V",""],"link_types":["in"],"nac_count":0,"nodes":[{"key":0,"label":"US","color":"black","width":34,"height":15,"definition":"type:US","visible_label":[{"text":"US","color":"black"}]},{"key":1,"label":"E","color":"black","width":34,"height":30,"definition":"del:type:E;new:type:V","visible_label":[{"text":"-E","color":"blue"},{"text":"+V","color":"green"}]},{"key":2,"label":"","color":"red","width":14,"height":15,"definition":"not::type:","visible_label":[{"text":"","color":"red"}]},{"key":3,"label":"","color":"red","width":14,"height":15,"definition":"not::type:","visible_label":[{"text":"","color":"red"}]},{"key":4,"label":"V","color":"red","width":24,"height":15,"definition":"not::type:V","visible_label":[{"text":"V","color":"red"}]}],"links":[{"key":"1-0_type:in","source":1,"target":0,"label":"in","color":"black","definition":"type:in","marker_id":"in","visible_label":[{"text":"in","color":"black"}]},{"key":"1-2_not::type:in","source":1,"target":2,"label":"in","color":"red","definition":"not::type:in","marker_id":"in","visible_label":[{"text":"in","color":"red"}]},{"key":"3-1_not::type:in","source":3,"target":1,"label":"in","color":"red","definition":"not::type:in","marker_id":"in","visible_label":[{"text":"in","color":"red"}]},{"key":"4-0_not::type:in","source":4,"target":0,"label":"in","color":"red","definition":"not::type:in","marker_id":"in","visible_label":[{"text":"in","color":"red"}]}]},{"name":"substantial_whole1","node_types":["E","Sw","J",""],"link_types":["in"],"nac_count":0,"nodes":[{"key":0,"label":"E","color":"black","width":44,"height":30,"definition":"del:type:E;new:type:Sw","visible_label":[{"text":"-E","color":"blue"},{"text":"+Sw","color":"green"}]},{"key":1,"label":"J","color":"black","width":24,"height":15,"definition":"type:J","visible_label":[{"text":"J","color":"black"}]},{"key":2,"label":"","color":"black","width":14,"height":15,"definition":"type:","visible_label":[{"text":"","color":"black"}]}],"links":[{"key":"1-0_type:in","source":1,"target":0,"label":"in","color":"black","definition":"type:in","marker_id":"in","visible_label":[{"text":"in","color":"black"}]},{"key":"0-2_type:in","source":0,"target":2,"label":"in","color":"black","definition":"type:in","marker_id":"in","visible_label":[{"text":"in","color":"black"}]}]},{"name":"substantial_whole2","node_types":["E","Sw","D",""],"link_types":["in"],"nac_count":0,"nodes":[{"key":0,"label":"E","color":"black","width":44,"height":30,"definition":"del:type:E;new:type:Sw","visible_label":[{"text":"-E","color":"blue"},{"text":"+Sw","color":"green"}]},{"key":1,"label":"D","color":"black","width":24,"height":15,"definition":"type:D","visible_label":[{"text":"D","color":"black"}]},{"key":2,"label":"","color":"black","width":14,"height":15,"definition":"type:","visible_label":[{"text":"","color":"black"}]}],"links":[{"key":"1-0_type:in","source":1,"target":0,"label":"in","color":"black","definition":"type:in","marker_id":"in","visible_label":[{"text":"in","color":"black"}]},{"key":"0-2_type:in","source":0,"target":2,"label":"in","color":"black","definition":"type:in","marker_id":"in","visible_label":[{"text":"in","color":"black"}]}]},{"name":"quality1","node_types":["E","Q","U","Sw"],"link_types":["in"],"nac_count":0,"nodes":[{"key":0,"label":"E","color":"black","width":34,"height":30,"definition":"del:type:E;new:type:Q","visible_label":[{"text":"-E","color":"blue"},{"text":"+Q","color":"green"}]},{"key":1,"label":"U","color":"black","width":24,"height":15,"definition":"type:U","visible_label":[{"text":"U","color":"black"}]},{"key":2,"label":"Sw","color":"black","width":34,"height":15,"definition":"type:Sw","visible_label":[{"text":"Sw","color":"black"}]}],"links":[{"key":"1-0_type:in","source":1,"target":0,"label":"in","color":"black","definition":"type:in","marker_id":"in","visible_label":[{"text":"in","color":"black"}]},{"key":"0-2_type:in","source":0,"target":2,"label":"in","color":"black","definition":"type:in","marker_id":"in","visible_label":[{"text":"in","color":"black"}]}]},{"name":"quality2","node_types":["E","Q","U","US"],"link_types":["in"],"nac_count":0,"nodes":[{"key":0,"label":"E","color":"black","width":34,"height":30,"definition":"del:type:E;new:type:Q","visible_label":[{"text":"-E","color":"blue"},{"text":"+Q","color":"green"}]},{"key":1,"label":"U","color":"black","width":24,"height":15,"definition":"type:U","visible_label":[{"text":"U","color":"black"}]},{"key":2,"label":"US","color":"black","width":34,"height":15,"definition":"type:US","visible_label":[{"text":"US","color":"black"}]}],"links":[{"key":"1-0_type:in","source":1,"target":0,"label":"in","color":"black","definition":"type:in","marker_id":"in","visible_label":[{"text":"in","color":"black"}]},{"key":"0-2_type:in","source":0,"target":2,"label":"in","color":"black","definition":"type:in","marker_id":"in","visible_label":[{"text":"in","color":"black"}]}]}],
"markers_list":["in","sv","con","dis","likes","-hello","-con_+dis","-dis_+con","?[in,sv]","+sv_-in","type:in","d","f",""],
"graph":1}
